spaceone/__init__.py
spaceone/dashboard/__init__.py
spaceone/dashboard/conf/__init__.py
spaceone/dashboard/conf/global_conf.py
spaceone/dashboard/conf/proto_conf.py
spaceone/dashboard/connector/__init__.py
spaceone/dashboard/error/__init__.py
spaceone/dashboard/error/common_dashboard.py
spaceone/dashboard/info/__init__.py
spaceone/dashboard/info/common_info.py
spaceone/dashboard/info/custom_widget_info.py
spaceone/dashboard/info/domain_dashboard_info.py
spaceone/dashboard/info/domain_dashboard_version_info.py
spaceone/dashboard/info/project_dashboard_info.py
spaceone/dashboard/info/project_dashboard_version_info.py
spaceone/dashboard/interface/__init__.py
spaceone/dashboard/interface/grpc/__init__.py
spaceone/dashboard/interface/grpc/v1/__init__.py
spaceone/dashboard/interface/grpc/v1/custom_widget.py
spaceone/dashboard/interface/grpc/v1/domain_dashboard.py
spaceone/dashboard/interface/grpc/v1/project_dashboard.py
spaceone/dashboard/lib/__init__.py
spaceone/dashboard/manager/__init__.py
spaceone/dashboard/manager/custom_widget_manager.py
spaceone/dashboard/manager/domain_dashboard_manager.py
spaceone/dashboard/manager/domain_dashboard_version_manager.py
spaceone/dashboard/manager/project_dashboard_manager.py
spaceone/dashboard/manager/project_dashboard_version_manager.py
spaceone/dashboard/model/__init__.py
spaceone/dashboard/model/custom_widget_model.py
spaceone/dashboard/model/domain_dashboard_model.py
spaceone/dashboard/model/domain_dashboard_version_model.py
spaceone/dashboard/model/project_dashboard_model.py
spaceone/dashboard/model/project_dashboard_version_model.py
spaceone/dashboard/service/__init__.py
spaceone/dashboard/service/custom_widget_service.py
spaceone/dashboard/service/domain_dashboard_service.py
spaceone/dashboard/service/project_dashboard_service.py
spaceone_dashboard-1.12.0.dist-info/METADATA
spaceone_dashboard-1.12.0.dist-info/WHEEL
spaceone_dashboard-1.12.0.dist-info/top_level.txt
spaceone_dashboard-1.12.0.dist-info/RECORD
